[
    {"name":"Home","url":"\/","item_model":"custom","model_name":"Custom",
    "children":[
        ]
    },
        
        {"name":"Adventure","url":"\/tour","item_model":"custom","model_name":"Custom",
            "children":[
                {"name":"Adventure List","url":"\/tour","item_model":"custom","model_name":"Custom","children":[]},
                {"name":"Adventure Map","url":"\/tour?_layout=map","item_model":"custom","model_name":"Custom","children":[]},
                {"name":"Adventure Detail","url":"\/tour\/paris-vacation-travel","item_model":"custom","model_name":"Custom","children":[]}
            ]
        },
        {"name":"Grooming","url":"\/space","item_model":"custom","model_name":"Custom",
            "children":[
                {"name":"Grooming List","url":"\/space","item_model":"custom","model_name":"Custom","children":[]},
                {"name":"Grooming Map","url":"\/space?_layout=map","item_model":"custom","model_name":"Custom","children":[]},
                {"name":"Grooming Detail","url":"\/space\/stay-greenwich-village","item_model":"custom","model_name":"Custom","children":[]}
            ]
        },
        {"name":"Car Washing","url":"\/#","item_model":"custom","model_name":"Custom",
                "children":[
                    {"name":"Car Washing List","url":"\/#","item_model":"custom","model_name":"Custom","children":[]},
                    {"name":"Car Washing Map","url":"\/#?_layout=map","item_model":"custom","model_name":"Custom","children":[]},
                    {"name":"Car Washing Detail","url":"\/#\/vinfast-lux-a20-plus","item_model":"custom","model_name":"Custom","children":[]}
                    ]
        },
        {"name":"Eatery","url":"\/#","item_model":"custom","model_name":"Custom",
                "children":[
                    {"name":"Event List","url":"\/#","item_model":"custom","model_name":"Custom","children":[]},
                    {"name":"Event Map","url":"\/#?_layout=map","item_model":"custom","model_name":"Custom","children":[]},
                    {"name":"Event Detail","url":"\/#\/aspen-glade-weddings-events","item_model":"custom","model_name":"Custom","children":[]}
                    ]
        },
        {"name":"Flight","url":"\/#","item_model":"custom","model_name":"Custom",
            "children":[
                {"name":"Flight List","url":"\/flight","item_model":"custom","model_name":"Custom","children":[]},
                {"name":"Flight Map","url":"\/flight?_layout=map","item_model":"custom","model_name":"Custom","children":[]}
                ]
    },
        
        {"name":"Pages","url":"#","item_model":"custom","model_name":"Custom",
            "children":[
                {"name":"News List","url":"\/news","item_model":"custom","model_name":"Custom","children":[]},
                {"name":"News Detail","url":"\/news\/morning-in-the-northern-sea","item_model":"custom","model_name":"Custom","children":[]},
                {"name":"Location Detail","url":"\/location\/paris","item_model":"custom","children":[]},
                {"name":"Become a vendor","url":"\/page\/become-a-vendor","item_model":"custom","children":[]},
                {"name":"Contact","url":"\/contact","item_model":"custom","model_name":"Custom","children":[]}
            ]
        }
    ]